<?xml version="1.0" encoding="ISO-8859-1"?>
<attributes>
<attribute>
<srcPos sline="0" eline="0" spos="0" epos="0"/>
<jmpPos sline="3" eline="3" spos="0" epos="0"/>
<text info="Signature: Ljava/util/Comparator<-TK;>;" aType="SignatureTag"/>
</attribute>
<attribute>
<srcPos sline="0" eline="0" spos="0" epos="0"/>
<jmpPos sline="4" eline="4" spos="0" epos="0"/>
<text info="Signature: Ljava/util/TreeMap$Entry<TK;TV;>;" aType="SignatureTag"/>
</attribute>
<attribute>
<srcPos sline="0" eline="0" spos="0" epos="0"/>
<jmpPos sline="7" eline="7" spos="0" epos="0"/>
<text info="Signature: Ljava/util/TreeMap<TK;TV;>.EntrySet;" aType="SignatureTag"/>
</attribute>
<attribute>
<srcPos sline="0" eline="0" spos="0" epos="0"/>
<jmpPos sline="8" eline="8" spos="0" epos="0"/>
<text info="Signature: Ljava/util/TreeMap$KeySet<TK;>;" aType="SignatureTag"/>
</attribute>
<attribute>
<srcPos sline="0" eline="0" spos="0" epos="0"/>
<jmpPos sline="9" eline="9" spos="0" epos="0"/>
<text info="Signature: Ljava/util/NavigableMap<TK;TV;>;" aType="SignatureTag"/>
</attribute>
<attribute>
<srcPos sline="0" eline="0" spos="0" epos="0"/>
<jmpPos sline="11" eline="11" spos="0" epos="0"/>
<text info="ConstantValue: 0" aType="IntegerConstantValueTag"/>
</attribute>
<attribute>
<srcPos sline="0" eline="0" spos="0" epos="0"/>
<jmpPos sline="12" eline="12" spos="0" epos="0"/>
<text info="ConstantValue: 1" aType="IntegerConstantValueTag"/>
</attribute>
<attribute>
<srcPos sline="0" eline="0" spos="0" epos="0"/>
<jmpPos sline="13" eline="13" spos="0" epos="0"/>
<text info="ConstantValue: 919286545866124006" aType="LongConstantValueTag"/>
</attribute>
<attribute>
<srcPos sline="159" eline="159" spos="0" epos="0"/>
<jmpPos sline="31" eline="31" spos="0" epos="0"/>
<text info="Signature: (Ljava/util/Comparator<-TK;>;)V" aType="SignatureTag"/>
</attribute>
<attribute>
<srcPos sline="177" eline="177" spos="0" epos="0"/>
<jmpPos sline="49" eline="49" spos="0" epos="0"/>
<text info="Signature: (Ljava/util/Map<+TK;+TV;>;)V" aType="SignatureTag"/>
</attribute>
<attribute>
<srcPos sline="191" eline="191" spos="0" epos="0"/>
<jmpPos sline="68" eline="68" spos="0" epos="0"/>
<text info="Signature: (Ljava/util/SortedMap<TK;+TV;>;)V" aType="SignatureTag"/>
</attribute>
<attribute>
<srcPos sline="272" eline="272" spos="0" epos="0"/>
<jmpPos sline="176" eline="176" spos="0" epos="0"/>
<text info="Signature: (Ljava/lang/Object;)TV;" aType="SignatureTag"/>
</attribute>
<attribute>
<srcPos sline="277" eline="277" spos="0" epos="0"/>
<jmpPos sline="197" eline="197" spos="0" epos="0"/>
<text info="Signature: ()Ljava/util/Comparator<-TK;>;" aType="SignatureTag"/>
</attribute>
<attribute>
<srcPos sline="284" eline="284" spos="0" epos="0"/>
<jmpPos sline="207" eline="207" spos="0" epos="0"/>
<text info="Signature: ()TK;" aType="SignatureTag"/>
</attribute>
<attribute>
<srcPos sline="291" eline="291" spos="0" epos="0"/>
<jmpPos sline="219" eline="219" spos="0" epos="0"/>
<text info="Signature: ()TK;" aType="SignatureTag"/>
</attribute>
<attribute>
<srcPos sline="307" eline="307" spos="0" epos="0"/>
<jmpPos sline="231" eline="231" spos="0" epos="0"/>
<text info="Signature: (Ljava/util/Map<+TK;+TV;>;)V" aType="SignatureTag"/>
</attribute>
<attribute>
<srcPos sline="338" eline="338" spos="0" epos="0"/>
<jmpPos sline="299" eline="299" spos="0" epos="0"/>
<text info="Signature: (Ljava/lang/Object;)Ljava/util/TreeMap$Entry<TK;TV;>;" aType="SignatureTag"/>
</attribute>
<attribute>
<srcPos sline="363" eline="363" spos="0" epos="0"/>
<jmpPos sline="354" eline="354" spos="0" epos="0"/>
<text info="Signature: (Ljava/lang/Object;)Ljava/util/TreeMap$Entry<TK;TV;>;" aType="SignatureTag"/>
</attribute>
<attribute>
<srcPos sline="387" eline="387" spos="0" epos="0"/>
<jmpPos sline="396" eline="396" spos="0" epos="0"/>
<text info="Signature: (TK;)Ljava/util/TreeMap$Entry<TK;TV;>;" aType="SignatureTag"/>
</attribute>
<attribute>
<srcPos sline="419" eline="419" spos="0" epos="0"/>
<jmpPos sline="459" eline="459" spos="0" epos="0"/>
<text info="Signature: (TK;)Ljava/util/TreeMap$Entry<TK;TV;>;" aType="SignatureTag"/>
</attribute>
<attribute>
<srcPos sline="453" eline="453" spos="0" epos="0"/>
<jmpPos sline="522" eline="522" spos="0" epos="0"/>
<text info="Signature: (TK;)Ljava/util/TreeMap$Entry<TK;TV;>;" aType="SignatureTag"/>
</attribute>
<attribute>
<srcPos sline="484" eline="484" spos="0" epos="0"/>
<jmpPos sline="580" eline="580" spos="0" epos="0"/>
<text info="Signature: (TK;)Ljava/util/TreeMap$Entry<TK;TV;>;" aType="SignatureTag"/>
</attribute>
<attribute>
<srcPos sline="528" eline="528" spos="0" epos="0"/>
<jmpPos sline="638" eline="638" spos="0" epos="0"/>
<text info="Signature: (TK;TV;)TV;" aType="SignatureTag"/>
</attribute>
<attribute>
<srcPos sline="594" eline="594" spos="0" epos="0"/>
<jmpPos sline="747" eline="747" spos="0" epos="0"/>
<text info="Signature: (Ljava/lang/Object;)TV;" aType="SignatureTag"/>
</attribute>
<attribute>
<srcPos sline="651" eline="651" spos="0" epos="0"/>
<jmpPos sline="844" eline="844" spos="0" epos="0"/>
<text info="Signature: ()Ljava/util/Map$Entry<TK;TV;>;" aType="SignatureTag"/>
</attribute>
<attribute>
<srcPos sline="658" eline="658" spos="0" epos="0"/>
<jmpPos sline="856" eline="856" spos="0" epos="0"/>
<text info="Signature: ()Ljava/util/Map$Entry<TK;TV;>;" aType="SignatureTag"/>
</attribute>
<attribute>
<srcPos sline="665" eline="665" spos="0" epos="0"/>
<jmpPos sline="868" eline="868" spos="0" epos="0"/>
<text info="Signature: ()Ljava/util/Map$Entry<TK;TV;>;" aType="SignatureTag"/>
</attribute>
<attribute>
<srcPos sline="676" eline="676" spos="0" epos="0"/>
<jmpPos sline="885" eline="885" spos="0" epos="0"/>
<text info="Signature: ()Ljava/util/Map$Entry<TK;TV;>;" aType="SignatureTag"/>
</attribute>
<attribute>
<srcPos sline="691" eline="691" spos="0" epos="0"/>
<jmpPos sline="902" eline="902" spos="0" epos="0"/>
<text info="Signature: (TK;)Ljava/util/Map$Entry<TK;TV;>;" aType="SignatureTag"/>
</attribute>
<attribute>
<srcPos sline="702" eline="702" spos="0" epos="0"/>
<jmpPos sline="916" eline="916" spos="0" epos="0"/>
<text info="Signature: (TK;)TK;" aType="SignatureTag"/>
</attribute>
<attribute>
<srcPos sline="713" eline="713" spos="0" epos="0"/>
<jmpPos sline="929" eline="929" spos="0" epos="0"/>
<text info="Signature: (TK;)Ljava/util/Map$Entry<TK;TV;>;" aType="SignatureTag"/>
</attribute>
<attribute>
<srcPos sline="724" eline="724" spos="0" epos="0"/>
<jmpPos sline="943" eline="943" spos="0" epos="0"/>
<text info="Signature: (TK;)TK;" aType="SignatureTag"/>
</attribute>
<attribute>
<srcPos sline="735" eline="735" spos="0" epos="0"/>
<jmpPos sline="956" eline="956" spos="0" epos="0"/>
<text info="Signature: (TK;)Ljava/util/Map$Entry<TK;TV;>;" aType="SignatureTag"/>
</attribute>
<attribute>
<srcPos sline="746" eline="746" spos="0" epos="0"/>
<jmpPos sline="970" eline="970" spos="0" epos="0"/>
<text info="Signature: (TK;)TK;" aType="SignatureTag"/>
</attribute>
<attribute>
<srcPos sline="757" eline="757" spos="0" epos="0"/>
<jmpPos sline="983" eline="983" spos="0" epos="0"/>
<text info="Signature: (TK;)Ljava/util/Map$Entry<TK;TV;>;" aType="SignatureTag"/>
</attribute>
<attribute>
<srcPos sline="768" eline="768" spos="0" epos="0"/>
<jmpPos sline="997" eline="997" spos="0" epos="0"/>
<text info="Signature: (TK;)TK;" aType="SignatureTag"/>
</attribute>
<attribute>
<srcPos sline="797" eline="797" spos="0" epos="0"/>
<jmpPos sline="1010" eline="1010" spos="0" epos="0"/>
<text info="Signature: ()Ljava/util/Set<TK;>;" aType="SignatureTag"/>
</attribute>
<attribute>
<srcPos sline="804" eline="804" spos="0" epos="0"/>
<jmpPos sline="1020" eline="1020" spos="0" epos="0"/>
<text info="Signature: ()Ljava/util/NavigableSet<TK;>;" aType="SignatureTag"/>
</attribute>
<attribute>
<srcPos sline="812" eline="812" spos="0" epos="0"/>
<jmpPos sline="1042" eline="1042" spos="0" epos="0"/>
<text info="Signature: ()Ljava/util/NavigableSet<TK;>;" aType="SignatureTag"/>
</attribute>
<attribute>
<srcPos sline="831" eline="831" spos="0" epos="0"/>
<jmpPos sline="1054" eline="1054" spos="0" epos="0"/>
<text info="Signature: ()Ljava/util/Collection<TV;>;" aType="SignatureTag"/>
</attribute>
<attribute>
<srcPos sline="851" eline="851" spos="0" epos="0"/>
<jmpPos sline="1077" eline="1077" spos="0" epos="0"/>
<text info="Signature: ()Ljava/util/Set<Ljava/util/Map$Entry<TK;TV;>;>;" aType="SignatureTag"/>
</attribute>
<attribute>
<srcPos sline="859" eline="859" spos="0" epos="0"/>
<jmpPos sline="1099" eline="1099" spos="0" epos="0"/>
<text info="Signature: ()Ljava/util/NavigableMap<TK;TV;>;" aType="SignatureTag"/>
</attribute>
<attribute>
<srcPos sline="876" eline="876" spos="0" epos="0"/>
<jmpPos sline="1122" eline="1122" spos="0" epos="0"/>
<text info="Signature: (TK;ZTK;Z)Ljava/util/NavigableMap<TK;TV;>;" aType="SignatureTag"/>
</attribute>
<attribute>
<srcPos sline="890" eline="890" spos="0" epos="0"/>
<jmpPos sline="1139" eline="1139" spos="0" epos="0"/>
<text info="Signature: (TK;Z)Ljava/util/NavigableMap<TK;TV;>;" aType="SignatureTag"/>
</attribute>
<attribute>
<srcPos sline="904" eline="904" spos="0" epos="0"/>
<jmpPos sline="1154" eline="1154" spos="0" epos="0"/>
<text info="Signature: (TK;Z)Ljava/util/NavigableMap<TK;TV;>;" aType="SignatureTag"/>
</attribute>
<attribute>
<srcPos sline="917" eline="917" spos="0" epos="0"/>
<jmpPos sline="1169" eline="1169" spos="0" epos="0"/>
<text info="Signature: (TK;TK;)Ljava/util/SortedMap<TK;TV;>;" aType="SignatureTag"/>
</attribute>
<attribute>
<srcPos sline="928" eline="928" spos="0" epos="0"/>
<jmpPos sline="1182" eline="1182" spos="0" epos="0"/>
<text info="Signature: (TK;)Ljava/util/SortedMap<TK;TV;>;" aType="SignatureTag"/>
</attribute>
<attribute>
<srcPos sline="939" eline="939" spos="0" epos="0"/>
<jmpPos sline="1194" eline="1194" spos="0" epos="0"/>
<text info="Signature: (TK;)Ljava/util/SortedMap<TK;TV;>;" aType="SignatureTag"/>
</attribute>
<attribute>
<srcPos sline="1017" eline="1017" spos="0" epos="0"/>
<jmpPos sline="1206" eline="1206" spos="0" epos="0"/>
<text info="Signature: ()Ljava/util/Iterator<TK;>;" aType="SignatureTag"/>
</attribute>
<attribute>
<srcPos sline="1021" eline="1021" spos="0" epos="0"/>
<jmpPos sline="1219" eline="1219" spos="0" epos="0"/>
<text info="Signature: ()Ljava/util/Iterator<TK;>;" aType="SignatureTag"/>
</attribute>
<attribute>
<srcPos sline="1203" eline="1203" spos="0" epos="0"/>
<jmpPos sline="1283" eline="1283" spos="0" epos="0"/>
<text info="Signature: <K:Ljava/lang/Object;V:Ljava/lang/Object;>(Ljava/util/TreeMap$Entry<TK;TV;>;)Ljava/util/Map$Entry<TK;TV;>;" aType="SignatureTag"/>
</attribute>
<attribute>
<srcPos sline="1211" eline="1211" spos="0" epos="0"/>
<jmpPos sline="1302" eline="1302" spos="0" epos="0"/>
<text info="Signature: <K:Ljava/lang/Object;V:Ljava/lang/Object;>(Ljava/util/TreeMap$Entry<TK;TV;>;)TK;" aType="SignatureTag"/>
</attribute>
<attribute>
<srcPos sline="1219" eline="1219" spos="0" epos="0"/>
<jmpPos sline="1320" eline="1320" spos="0" epos="0"/>
<text info="Signature: <K:Ljava/lang/Object;>(Ljava/util/TreeMap$Entry<TK;*>;)TK;" aType="SignatureTag"/>
</attribute>
<attribute>
<srcPos sline="1961" eline="1961" spos="0" epos="0"/>
<jmpPos sline="1338" eline="1338" spos="0" epos="0"/>
<text info="Signature: ()Ljava/util/TreeMap$Entry<TK;TV;>;" aType="SignatureTag"/>
</attribute>
<attribute>
<srcPos sline="1973" eline="1973" spos="0" epos="0"/>
<jmpPos sline="1358" eline="1358" spos="0" epos="0"/>
<text info="Signature: ()Ljava/util/TreeMap$Entry<TK;TV;>;" aType="SignatureTag"/>
</attribute>
<attribute>
<srcPos sline="1984" eline="1984" spos="0" epos="0"/>
<jmpPos sline="1378" eline="1378" spos="0" epos="0"/>
<text info="Signature: <K:Ljava/lang/Object;V:Ljava/lang/Object;>(Ljava/util/TreeMap$Entry<TK;TV;>;)Ljava/util/TreeMap$Entry<TK;TV;>;" aType="SignatureTag"/>
</attribute>
<attribute>
<srcPos sline="2006" eline="2006" spos="0" epos="0"/>
<jmpPos sline="1421" eline="1421" spos="0" epos="0"/>
<text info="Signature: <K:Ljava/lang/Object;V:Ljava/lang/Object;>(Ljava/util/TreeMap$Entry<TK;TV;>;)Ljava/util/TreeMap$Entry<TK;TV;>;" aType="SignatureTag"/>
</attribute>
<attribute>
<srcPos sline="2035" eline="2035" spos="0" epos="0"/>
<jmpPos sline="1464" eline="1464" spos="0" epos="0"/>
<text info="Signature: <K:Ljava/lang/Object;V:Ljava/lang/Object;>(Ljava/util/TreeMap$Entry<TK;TV;>;)Z" aType="SignatureTag"/>
</attribute>
<attribute>
<srcPos sline="2039" eline="2039" spos="0" epos="0"/>
<jmpPos sline="1482" eline="1482" spos="0" epos="0"/>
<text info="Signature: <K:Ljava/lang/Object;V:Ljava/lang/Object;>(Ljava/util/TreeMap$Entry<TK;TV;>;)Ljava/util/TreeMap$Entry<TK;TV;>;" aType="SignatureTag"/>
</attribute>
<attribute>
<srcPos sline="2043" eline="2043" spos="0" epos="0"/>
<jmpPos sline="1499" eline="1499" spos="0" epos="0"/>
<text info="Signature: <K:Ljava/lang/Object;V:Ljava/lang/Object;>(Ljava/util/TreeMap$Entry<TK;TV;>;Z)V" aType="SignatureTag"/>
</attribute>
<attribute>
<srcPos sline="2048" eline="2048" spos="0" epos="0"/>
<jmpPos sline="1514" eline="1514" spos="0" epos="0"/>
<text info="Signature: <K:Ljava/lang/Object;V:Ljava/lang/Object;>(Ljava/util/TreeMap$Entry<TK;TV;>;)Ljava/util/TreeMap$Entry<TK;TV;>;" aType="SignatureTag"/>
</attribute>
<attribute>
<srcPos sline="2052" eline="2052" spos="0" epos="0"/>
<jmpPos sline="1531" eline="1531" spos="0" epos="0"/>
<text info="Signature: <K:Ljava/lang/Object;V:Ljava/lang/Object;>(Ljava/util/TreeMap$Entry<TK;TV;>;)Ljava/util/TreeMap$Entry<TK;TV;>;" aType="SignatureTag"/>
</attribute>
<attribute>
<srcPos sline="2057" eline="2057" spos="0" epos="0"/>
<jmpPos sline="1548" eline="1548" spos="0" epos="0"/>
<text info="Signature: (Ljava/util/TreeMap$Entry<TK;TV;>;)V" aType="SignatureTag"/>
</attribute>
<attribute>
<srcPos sline="2076" eline="2076" spos="0" epos="0"/>
<jmpPos sline="1596" eline="1596" spos="0" epos="0"/>
<text info="Signature: (Ljava/util/TreeMap$Entry<TK;TV;>;)V" aType="SignatureTag"/>
</attribute>
<attribute>
<srcPos sline="2093" eline="2093" spos="0" epos="0"/>
<jmpPos sline="1644" eline="1644" spos="0" epos="0"/>
<text info="Signature: (Ljava/util/TreeMap$Entry<TK;TV;>;)V" aType="SignatureTag"/>
</attribute>
<attribute>
<srcPos sline="2137" eline="2137" spos="0" epos="0"/>
<jmpPos sline="1751" eline="1751" spos="0" epos="0"/>
<text info="Signature: (Ljava/util/TreeMap$Entry<TK;TV;>;)V" aType="SignatureTag"/>
</attribute>
<attribute>
<srcPos sline="2186" eline="2186" spos="0" epos="0"/>
<jmpPos sline="1867" eline="1867" spos="0" epos="0"/>
<text info="Signature: (Ljava/util/TreeMap$Entry<TK;TV;>;)V" aType="SignatureTag"/>
</attribute>
<attribute>
<srcPos sline="2295" eline="2295" spos="0" epos="0"/>
<jmpPos sline="2048" eline="2048" spos="0" epos="0"/>
<text info="Signature: (ILjava/io/ObjectInputStream;TV;)V" aType="SignatureTag"/>
</attribute>
<attribute>
<srcPos sline="2301" eline="2301" spos="0" epos="0"/>
<jmpPos sline="2063" eline="2063" spos="0" epos="0"/>
<text info="Signature: (Ljava/util/SortedSet<+TK;>;TV;)V" aType="SignatureTag"/>
</attribute>
<attribute>
<srcPos sline="2342" eline="2342" spos="0" epos="0"/>
<jmpPos sline="2101" eline="2101" spos="0" epos="0"/>
<text info="Signature: (ILjava/util/Iterator;Ljava/io/ObjectInputStream;TV;)V" aType="SignatureTag"/>
</attribute>
<attribute>
<srcPos sline="2379" eline="2379" spos="0" epos="0"/>
<jmpPos sline="2123" eline="2123" spos="0" epos="0"/>
<text info="Signature: (IIIILjava/util/Iterator;Ljava/io/ObjectInputStream;TV;)Ljava/util/TreeMap$Entry<TK;TV;>;" aType="SignatureTag"/>
</attribute>
</attributes>
