<?xml version="1.0" encoding="ISO-8859-1"?>
<attributes>
<attribute>
<srcPos sline="0" eline="0" spos="0" epos="0"/>
<jmpPos sline="3" eline="3" spos="0" epos="0"/>
<text info="ConstantValue: -5024744406713321676" aType="LongConstantValueTag"/>
</attribute>
<attribute>
<srcPos sline="0" eline="0" spos="0" epos="0"/>
<jmpPos sline="4" eline="4" spos="0" epos="0"/>
<text info="Signature: Ljava/util/HashMap<TE;Ljava/lang/Object;>;" aType="SignatureTag"/>
</attribute>
<attribute>
<srcPos sline="114" eline="114" spos="0" epos="0"/>
<jmpPos sline="20" eline="20" spos="0" epos="0"/>
<text info="Signature: (Ljava/util/Collection<+TE;>;)V" aType="SignatureTag"/>
</attribute>
<attribute>
<srcPos sline="169" eline="169" spos="0" epos="0"/>
<jmpPos sline="95" eline="95" spos="0" epos="0"/>
<text info="Signature: ()Ljava/util/Iterator<TE;>;" aType="SignatureTag"/>
</attribute>
<attribute>
<srcPos sline="216" eline="216" spos="0" epos="0"/>
<jmpPos sline="147" eline="147" spos="0" epos="0"/>
<text info="Signature: (TE;)Z" aType="SignatureTag"/>
</attribute>
</attributes>
