<?xml version="1.0" encoding="ISO-8859-1"?>
<attributes>
<attribute>
<srcPos sline="277" eline="277" spos="0" epos="0"/>
<jmpPos sline="811" eline="811" spos="0" epos="0"/>
<text info="Signature: (Ljava/net/SocketOption<Ljava/lang/Boolean;>;Z)V" aType="SignatureTag"/>
</attribute>
<attribute>
<srcPos sline="287" eline="287" spos="0" epos="0"/>
<jmpPos sline="843" eline="843" spos="0" epos="0"/>
<text info="Signature: (Ljava/net/SocketOption<Ljava/lang/Integer;>;I)V" aType="SignatureTag"/>
</attribute>
<attribute>
<srcPos sline="295" eline="295" spos="0" epos="0"/>
<jmpPos sline="875" eline="875" spos="0" epos="0"/>
<text info="Signature: (Ljava/net/SocketOption<Ljava/lang/Boolean;>;)Z" aType="SignatureTag"/>
</attribute>
<attribute>
<srcPos sline="304" eline="304" spos="0" epos="0"/>
<jmpPos sline="906" eline="906" spos="0" epos="0"/>
<text info="Signature: (Ljava/net/SocketOption<Ljava/lang/Integer;>;)I" aType="SignatureTag"/>
</attribute>
</attributes>
